formstorm/FormElement.py
formstorm/FormTest.py
formstorm/__init__.py
formstorm/iterhelpers.py
formstorm-1.0.dist-info/LICENSE
formstorm-1.0.dist-info/METADATA
formstorm-1.0.dist-info/WHEEL
formstorm-1.0.dist-info/top_level.txt
formstorm-1.0.dist-info/RECORD
