Metadata-Version: 2.1
Name: formstorm
Version: 1.0
Summary: FormStorm is a library that easily creates unit tests for Django forms.
Home-page: https://github.com/TravisDart/formstorm/
Author: Travis Dart
Author-email: git@travisdart.com
License: MIT
Platform: UNKNOWN
Classifier: Framework :: Django
Classifier: Intended Audience :: Developers
Classifier: License :: OSI Approved :: MIT License
Classifier: Operating System :: OS Independent
Classifier: Framework :: Django
Classifier: Programming Language :: Python
Classifier: Topic :: Software Development :: Testing
